{"all":{"武汉":277,"芜湖":52,"南京":182,"长沙":256,"杭州":904,"牡丹江":16,"昆明":155,"湖州":294,"广州":578,"洛阳":141,"深圳":271,"遵义":3,"青岛":175,"连云港":54,"成都":877,"南昌":23,"天津":246,"台州":126,"丹东":34,"宁波":323,"泰州":24,"北京":763,"南通":57,"湛江":49,"淄博":78,"上海":886,"汕头":70,"河南":282,"苏州":308,"邢台":13,"义乌":95,"湘潭":33,"焦作":27,"乌鲁木齐":111,"温州":432,"沈阳":125,"西安":257,"济南":114,"株洲":24,"吉林":71,"广西":200,"太仓":36,"绍兴":427,"石家庄":72,"重庆":341,"烟台":36,"嘉兴":151,"常德":70,"海门":6,"福州":72,"泉州":57,"泸州":64,"肇庆":20,"南充":24,"营口":47,"兰州":66,"厦门":34,"中山":158,"沧州":60,"哈尔滨":197,"保定":61,"常州":39,"镇江":149,"珠海":70,"贵阳":38,"廊坊":86,"无锡":181,"金华":126,"合肥":80,"盐城":56,"枣庄":32,"江阴":180,"鞍山":36,"丽水":78,"银川":53,"郑州":119,"长春":27,"大连":135,"宜宾":6,"寿光":21,"德州":101,"太原":55,"江门":52,"扬州":46,"临汾":27,"九江":3,"潮州":54,"延安":6,"佛山":212,"莱芜":23,"东莞":75,"惠州":58,"舟山":38,"柳州":16,"大同":66,"汕尾":2,"安阳":18,"呼和浩特":25,"三门峡":37,"岳阳":2,"桂林":14,"秦皇岛":10,"吴江":40,"盘锦":13,"包头":24,"金坛":35,"徐州":19,"北海":9,"德阳":37,"潍坊":31,"马鞍山":27,"鄂尔多斯":19,"咸阳":6,"云南":56,"南宁":22,"昆山":65,"库尔勒":33,"宜兴":82,"海口":20,"淮安":37,"济宁":27,"茂名":75,"抚顺":16,"嘉峪关":3,"常熟":112,"泰安":8,"齐齐哈尔":9,"玉溪":16,"渭南":8,"绵阳":2,"揭阳":46,"诸暨":15,"宿迁":5,"衡水":42,"聊城":14,"承德":1,"葫芦岛":7,"梅州":10,"滨州":16,"阳泉":13,"临沂":19,"邯郸":35,"宝鸡":33,"威海":2,"荆州":22,"自贡":3,"三亚":6,"清远":10,"菏泽":4,"唐山":11,"张家口":7,"阳江":2,"曲靖":6,"平顶山":7,"开封":19,"宜昌":16,"克拉玛依":3,"河源":13,"赤峰":1,"张家界":4,"蓬莱":3,"大庆":19,"长治":1,"韶关":8},"MITOQ":{"武汉":8,"洛阳":2,"成都":392,"苏州":11,"海门":3,"昆明":8,"泰州":4,"沈阳":7,"福州":5,"上海":50,"泉州":4,"南京":12,"北京":30,"肇庆":1,"天津":20,"金华":4,"重庆":63,"杭州":21,"宁波":17,"厦门":1,"广州":25,"乌鲁木齐":3,"惠州":3,"泸州":27,"深圳":11,"河南":11,"安阳":7,"温州":9,"义乌":9,"济南":4,"西安":6,"包头":5,"金坛":4,"鄂尔多斯":8,"太原":6,"镇江":4,"长沙":6,"佛山":5,"银川":7,"台州":4,"南通":5,"兰州":14,"廊坊":4,"广西":5,"汕头":1,"徐州":4,"济宁":2,"中山":7,"芜湖":4,"德阳":2,"吉林":1,"珠海":4,"宜兴":3,"合肥":1,"三亚":1,"舟山":4,"无锡":7,"云南":5,"荆州":3,"遵义":2,"昆山":1,"宜昌":2,"绍兴":6,"东莞":2,"丹东":4,"湖州":4,"青岛":3,"长春":4,"曲靖":3,"郑州":21,"哈尔滨":3,"盐城":2,"宜宾":1,"石家庄":1,"德州":2,"鞍山":2,"沧州":6,"淄博":3,"营口":5,"开封":3,"南充":1,"江门":2,"丽水":1,"烟台":1,"长治":1,"潮州":1},"BIO-E":{"芜湖":3,"连云港":1,"广州":10,"武汉":10,"河南":5,"温州":3,"昆明":2,"杭州":30,"青岛":7,"贵阳":2,"绍兴":6,"丽水":2,"北京":33,"台州":7,"宁波":9,"扬州":3,"湖州":13,"重庆":4,"桂林":1,"深圳":3,"德州":2,"佛山":2,"中山":4,"淮安":2,"成都":15,"吉林":1,"西安":6,"上海":19,"兰州":2,"东莞":10,"洛阳":1,"长春":1,"金华":7,"苏州":9,"嘉兴":1,"银川":14,"马鞍山":2,"长沙":1,"义乌":3,"郑州":4,"玉溪":2,"厦门":4,"淄博":6,"江门":13,"广西":5,"三亚":1,"营口":4,"合肥":2,"宜昌":1,"哈尔滨":6,"河源":1,"珠海":2,"太仓":4,"德阳":2,"昆山":1,"石家庄":5,"潍坊":3,"常德":1,"邢台":1,"湘潭":2,"南京":5,"镇江":1,"大同":1,"保定":1,"济南":1,"太原":2,"宜兴":1,"大庆":1},"NATIO":{"南京":6,"湖州":5,"洛阳":2,"天津":5,"济南":3,"成都":4,"广州":23,"长沙":4,"哈尔滨":5,"温州":2,"合肥":7,"银川":1,"宁波":4,"北京":7,"太原":1,"延安":1,"台州":5,"潮州":1,"中山":2,"江门":1,"上海":10,"佛山":3,"无锡":3,"河南":5,"盐城":3,"昆明":5,"杭州":9,"苏州":1,"福州":2,"东莞":4,"沈阳":3,"常州":1,"青岛":3,"西安":3,"临沂":2,"重庆":5,"郑州":1,"柳州":4,"武汉":1,"绍兴":3,"芜湖":1,"昆山":3,"惠州":3,"深圳":4,"克拉玛依":1,"德州":1,"海口":1,"湘潭":4,"南宁":1,"徐州":1,"诸暨":1,"邯郸":1,"汕头":1,"淮安":1,"金华":3,"宜兴":4,"唐山":2,"连云港":1,"石家庄":1,"贵阳":1,"丹东":1},"LUCAS":{"南京":4,"西安":2,"杭州":16,"广州":10,"河南":2,"苏州":2,"合肥":3,"重庆":8,"绍兴":8,"台州":1,"厦门":2,"临汾":2,"沈阳":3,"南通":2,"中山":2,"成都":7,"长沙":11,"上海":6,"武汉":6,"淄博":2,"泰安":1,"湛江":2,"北京":7,"温州":3,"太原":1,"潮州":4,"长春":1,"湖州":5,"天津":3,"梅州":1,"无锡":6,"宁波":2,"广西":6,"衡水":1,"汕头":2,"马鞍山":1,"廊坊":1,"南充":1,"莱芜":2,"惠州":2,"深圳":3,"镇江":1,"淮安":1,"丽水":1,"青岛":1,"株洲":2,"佛山":4,"湘潭":1,"潍坊":2,"义乌":1,"珠海":2,"哈尔滨":1,"常熟":4,"包头":1,"揭阳":2,"宝鸡":2,"徐州":1,"泸州":1,"济宁":1},"DU'IT":{"长沙":1,"泰州":2,"河南":7,"吉林":1,"上海":16,"镇江":2,"常熟":1,"绍兴":16,"金坛":2,"深圳":2,"西安":4,"温州":3,"嘉兴":4,"玉溪":1,"合肥":3,"广西":1,"中山":3,"北京":9,"宁波":4,"芜湖":1,"沈阳":5,"无锡":4,"湛江":3,"湖州":3,"重庆":8,"石家庄":6,"张家界":1,"济南":1,"丽水":1,"杭州":6,"邯郸":1,"武汉":13,"南京":1,"苏州":1,"广州":1,"佛山":1,"营口":1,"淮安":2,"江阴":1,"宜昌":1,"肇庆":2,"徐州":1,"成都":1,"济宁":1,"贵阳":1},"REFRESH":{"长沙":1,"天津":4,"湛江":2,"无锡":1,"成都":2,"宁波":4,"南宁":1,"北京":2,"营口":3,"上海":3,"潮州":1,"芜湖":1,"苏州":1,"深圳":1,"吴江":1,"广州":1,"杭州":1,"哈尔滨":1,"镇江":1,"江阴":4,"金华":1},"ALPINE SILK":{"长沙":2,"中山":1,"杭州":6,"天津":4,"焦作":1,"成都":1,"绍兴":2,"武汉":3,"北京":5,"哈尔滨":2,"上海":1,"昆明":1,"湖州":2,"玉溪":1,"丽水":3,"温州":10,"芜湖":1,"南京":1,"常州":1,"苏州":6,"开封":1,"淮安":1,"徐州":1,"重庆":1,"昆山":1,"合肥":1,"乌鲁木齐":1,"衡水":3,"深圳":1,"珠海":1,"青岛":1,"宜兴":1,"连云港":1,"河南":1,"沧州":1,"宁波":1},"RED SEAL":{"杭州":48,"牡丹江":2,"南通":6,"苏州":17,"天津":15,"上海":29,"洛阳":2,"成都":29,"吉林":4,"济南":4,"泸州":1,"宁波":11,"武汉":12,"义乌":10,"镇江":6,"哈尔滨":14,"保定":6,"无锡":14,"河南":16,"温州":10,"湖州":16,"中山":8,"石家庄":13,"北京":31,"佛山":30,"秦皇岛":3,"昆明":1,"广州":26,"吴江":6,"鞍山":4,"芜湖":3,"枣庄":5,"德州":3,"徐州":2,"长沙":15,"云南":1,"丹东":4,"银川":5,"昆山":5,"珠海":2,"青岛":13,"嘉峪关":1,"泰安":1,"绍兴":28,"宜兴":7,"东莞":1,"呼和浩特":1,"广西":6,"盐城":1,"江阴":66,"南京":3,"深圳":9,"阳泉":1,"西安":29,"郑州":4,"潍坊":1,"三亚":1,"乌鲁木齐":6,"兰州":1,"沈阳":2,"延安":3,"海口":1,"金坛":2,"临汾":1,"库尔勒":4,"南充":5,"平顶山":1,"嘉兴":8,"台州":1,"衡水":5,"汕头":9,"惠州":3,"淮安":1,"大同":1,"沧州":1,"德阳":1,"茂名":2,"盘锦":2,"大庆":4,"丽水":1,"常德":3,"金华":2,"湛江":3,"福州":2,"宜昌":4,"烟台":1,"肇庆":5,"常熟":2,"宝鸡":4,"济宁":1},"REVIVE":{"牡丹江":2,"深圳":2,"自贡":1,"北京":9,"东莞":2,"宁波":1,"吴江":1,"河南":1,"杭州":1,"苏州":1,"昆山":1,"无锡":2,"长沙":1,"上海":3,"广西":1,"吉林":1},"CHUPA CHUPS":{"牡丹江":1,"杭州":4,"盘锦":1,"北京":2,"宁波":5,"武汉":1,"莱芜":3,"青岛":1,"上海":2,"绍兴":1,"临沂":1,"沈阳":1,"广州":4,"福州":3,"中山":1,"台州":1,"淄博":1,"湖州":1,"大同":1},"SWISSE":{"牡丹江":3,"湖州":21,"洛阳":17,"南昌":6,"丹东":1,"北京":47,"南通":6,"湛江":2,"连云港":5,"温州":29,"上海":49,"济南":12,"绍兴":47,"太仓":1,"昆明":14,"成都":52,"常德":6,"淄博":10,"深圳":20,"兰州":4,"镇江":19,"广州":40,"宁波":27,"青岛":10,"河南":21,"福州":2,"沈阳":5,"合肥":8,"盐城":4,"鞍山":2,"重庆":22,"苏州":30,"杭州":75,"大连":19,"泉州":2,"宜宾":3,"德州":8,"南京":10,"厦门":4,"潮州":10,"廊坊":6,"佛山":9,"丽水":4,"中山":26,"东莞":3,"长沙":16,"焦作":6,"大同":8,"武汉":24,"金华":7,"台州":6,"桂林":1,"秦皇岛":3,"哈尔滨":12,"潍坊":2,"马鞍山":4,"昆山":5,"枣庄":1,"海口":4,"江门":1,"惠州":4,"汕头":7,"沧州":4,"乌鲁木齐":4,"云南":5,"呼和浩特":2,"茂名":2,"三门峡":4,"莱芜":1,"诸暨":2,"芜湖":3,"长春":2,"扬州":3,"济宁":2,"常熟":15,"天津":21,"泰州":2,"江阴":8,"滨州":2,"无锡":7,"常州":3,"嘉兴":7,"湘潭":5,"临沂":4,"义乌":4,"郑州":19,"包头":5,"吉林":9,"威海":2,"宜兴":3,"宝鸡":2,"齐齐哈尔":2,"抚顺":4,"贵阳":1,"安阳":7,"太原":1,"烟台":1,"阳泉":9,"南宁":2,"张家口":1,"保定":6,"阳江":1,"盘锦":2,"金坛":2,"西安":5,"邯郸":8,"吴江":1,"泸州":1,"邢台":2,"海门":2,"广西":6,"衡水":4,"珠海":5,"大庆":2,"揭阳":4,"淮安":2,"石家庄":4,"宜昌":1,"清远":2},"NATURE'S BEAUTY":{"牡丹江":1,"洛阳":2,"沈阳":11,"镇江":1,"厦门":1,"上海":4,"北京":1,"寿光":6,"桂林":1,"天津":4,"鞍山":1,"贵阳":1,"河南":2,"长沙":2,"成都":3,"杭州":6,"常州":1,"常德":1,"宁波":4,"德州":3,"苏州":4,"玉溪":1,"泉州":5,"曲靖":1,"广州":2,"惠州":1,"石家庄":2,"张家口":1,"盐城":1,"青岛":3,"济南":1,"南京":3,"荆州":1,"德阳":1,"佛山":1,"南通":1,"宜昌":1,"金华":1},"OLIVADO":{"牡丹江":1,"淄博":2,"廊坊":6,"杭州":3,"临汾":1,"上海":4,"广州":6,"温州":3,"南通":2,"西安":1,"大连":3,"北京":8,"哈尔滨":8,"贵阳":1,"常德":1,"南京":2,"青岛":2,"武汉":2,"成都":1,"泉州":1,"中山":1,"广西":1,"湖州":1,"天津":3,"莱芜":1,"镇江":2,"金华":2,"江阴":8,"昆明":1,"济宁":2,"吉林":5,"河南":3,"宜兴":1,"潍坊":1,"长沙":3,"邢台":1,"滨州":1,"合肥":2,"济南":2,"连云港":1,"佛山":2,"丽水":2,"大庆":2,"石家庄":1,"大同":1,"无锡":1,"苏州":1},"MERINO":{"牡丹江":1,"嘉兴":3,"淄博":3,"上海":8,"重庆":5,"镇江":1,"苏州":2,"温州":5,"广州":12,"绍兴":5,"乌鲁木齐":2,"潮州":14,"沈阳":4,"杭州":6,"天津":3,"北京":4,"贵阳":1,"佛山":6,"合肥":3,"湛江":1,"长沙":3,"银川":1,"台州":1,"枣庄":1,"广西":2,"西安":3,"郑州":3,"柳州":1,"太原":4,"成都":6,"鞍山":1,"福州":1,"洛阳":1,"南京":2,"宁波":6,"义乌":1,"哈尔滨":6,"张家口":1,"泸州":1,"济南":1,"吴江":2,"潍坊":1,"深圳":1,"邯郸":4,"无锡":1,"扬州":1,"大连":2,"江阴":3,"石家庄":2,"连云港":1,"南昌":3,"云南":1,"北海":1,"徐州":1,"揭阳":2},"UNICHI":{"昆明":20,"青岛":7,"成都":17,"乌鲁木齐":4,"太仓":1,"杭州":25,"宁波":5,"广州":17,"苏州":5,"沈阳":8,"河南":6,"佛山":3,"舟山":3,"郑州":6,"天津":5,"嘉兴":2,"东莞":2,"连云港":7,"中山":4,"北京":23,"洛阳":4,"石家庄":6,"咸阳":3,"武汉":14,"绍兴":6,"温州":5,"长沙":1,"云南":1,"昆山":5,"珠海":2,"济南":1,"丽水":3,"呼和浩特":2,"焦作":3,"绵阳":2,"深圳":7,"扬州":5,"台州":3,"诸暨":2,"海口":2,"常德":2,"茂名":3,"常熟":1,"揭阳":2,"营口":5,"上海":17,"无锡":4,"重庆":14,"丹东":4,"马鞍山":2,"哈尔滨":3,"常州":1,"南昌":2,"太原":4,"贵阳":3,"鞍山":8,"义乌":2,"合肥":7,"兰州":2,"宝鸡":2,"三亚":1,"荆州":1,"镇江":7,"宜宾":2,"惠州":2,"南通":2,"西安":5,"宜兴":2,"柳州":1,"河源":1,"吉林":2,"沧州":4,"大同":1,"淄博":1,"鄂尔多斯":2,"南宁":2,"安阳":1,"泉州":1,"广西":2,"盐城":3},"BEES BRILLIANCE":{"湖州":1,"温州":1,"银川":2,"无锡":2,"廊坊":1,"济宁":1,"长沙":1,"成都":3,"绍兴":1,"北海":3,"玉溪":1,"北京":2,"上海":10,"广州":1,"淄博":1,"苏州":1,"青岛":1,"德阳":2,"潍坊":1,"洛阳":2,"汕头":1,"杭州":2,"嘉兴":2,"寿光":2,"大庆":1,"佛山":1,"临汾":3,"金华":2},"THOMPSONS":{"湖州":55,"武汉":7,"淄博":9,"上海":27,"汕头":2,"济南":5,"吉林":1,"洛阳":3,"杭州":23,"哈尔滨":12,"北京":40,"保定":8,"常州":4,"广州":13,"廊坊":5,"福州":2,"江阴":27,"苏州":5,"鞍山":1,"合肥":6,"佛山":6,"南京":6,"东莞":11,"大同":3,"安阳":1,"丽水":2,"深圳":8,"绍兴":5,"枣庄":3,"德州":4,"无锡":6,"云南":3,"昆山":2,"成都":2,"宁波":5,"金华":9,"温州":8,"乌鲁木齐":4,"西安":9,"芜湖":1,"重庆":19,"南充":2,"盐城":1,"湘潭":2,"泉州":1,"昆明":5,"邯郸":3,"焦作":1,"广西":3,"宝鸡":1,"包头":1,"葫芦岛":1,"聊城":1,"延安":1,"嘉兴":4,"长沙":5,"河南":4,"中山":1,"宜兴":2,"郑州":2,"兰州":1,"南宁":1,"大连":4,"沧州":3,"天津":4,"茂名":1,"台州":2,"太仓":2,"扬州":1,"开封":1,"淮安":3,"河源":1,"大庆":1,"衡水":1},"MANUKA HEALTH":{"广州":1,"泉州":2,"深圳":4,"上海":6,"丽水":3,"苏州":7,"杭州":13,"北京":10,"厦门":1,"枣庄":1,"南充":2,"合肥":1,"南通":3,"淄博":1,"无锡":2,"哈尔滨":7,"台州":1,"湖州":1,"温州":5,"江阴":5,"绍兴":1,"沈阳":1,"中山":1,"赤峰":1,"济宁":1,"南京":1,"佛山":3,"青岛":1,"沧州":1,"常州":1,"镇江":1,"河南":1,"大连":14,"舟山":1,"嘉兴":1,"廊坊":1,"邯郸":1,"常熟":1,"天津":2,"大庆":2,"宜兴":1,"鞍山":3},"HERBSENSE":{"广州":12,"上海":17,"杭州":13,"成都":6,"绍兴":1,"武汉":4,"乌鲁木齐":2,"深圳":3,"佛山":4,"湖州":4,"台州":3,"呼和浩特":1,"桂林":1,"济南":3,"哈尔滨":7,"北京":13,"廊坊":1,"昆山":2,"重庆":3,"宁波":5,"焦作":5,"河南":2,"洛阳":1,"大连":3,"淮安":2,"兰州":5,"泉州":3,"苏州":5,"丹东":2,"保定":1,"西安":3,"无锡":3,"开封":1,"汕头":1,"荆州":1,"天津":3,"温州":1,"惠州":1,"嘉兴":1,"太原":2,"长沙":1,"南京":2,"金华":2,"临沂":1,"常德":1,"邢台":1,"邯郸":1,"镇江":1,"常熟":1,"徐州":1,"青岛":1,"三门峡":2},"LIFE SPACE":{"广州":13,"济南":2,"嘉兴":3,"兰州":1,"宁波":8,"苏州":8,"沧州":3,"北京":17,"河南":7,"盐城":2,"杭州":12,"湛江":1,"金华":5,"太原":1,"青岛":5,"潮州":4,"深圳":9,"江门":1,"湖州":6,"江阴":1,"重庆":3,"绍兴":3,"福州":3,"包头":4,"中山":2,"金坛":3,"上海":20,"德州":1,"枣庄":1,"东莞":3,"镇江":5,"茂名":3,"天津":8,"南宁":1,"芜湖":1,"昆明":6,"廊坊":5,"武汉":15,"温州":5,"长沙":2,"成都":5,"无锡":5,"常德":2,"宜兴":1,"乌鲁木齐":3,"阳泉":1,"广西":2,"湘潭":5,"西安":1,"丹东":1,"衡水":2,"丽水":2,"鄂尔多斯":2,"昆山":2,"扬州":2,"荆州":1,"汕头":3,"梅州":1,"库尔勒":2,"洛阳":1,"揭阳":2,"烟台":1,"淄博":1,"哈尔滨":1,"佛山":4,"宿迁":1,"云南":1,"淮安":1},"JACK N JILL":{"广州":5,"丹东":1,"杭州":9,"青岛":3,"重庆":3,"临汾":1,"成都":6,"绍兴":1,"镇江":2,"北京":3,"西安":2,"上海":4,"大连":2,"荆州":1,"深圳":1,"吉林":6,"连云港":1,"宜兴":3,"湖州":2,"丽水":4,"河南":1,"常德":4,"常熟":1,"德州":1,"苏州":1,"廊坊":1},"CHANTELLE":{"洛阳":1,"珠海":2,"台州":2,"江门":2,"扬州":1,"上海":9,"昆明":2,"泰州":2,"成都":2,"马鞍山":1,"绍兴":2,"温州":2,"武汉":4,"天津":4,"杭州":3,"德州":2,"呼和浩特":1,"沈阳":3,"乌鲁木齐":2,"自贡":1,"广州":7,"嘉兴":5,"广西":3,"廊坊":1,"宁波":4,"深圳":2,"抚顺":1,"长沙":1,"中山":1,"芜湖":1,"保定":1,"佛山":1,"常德":1,"北京":4,"银川":1,"镇江":1,"丽水":1,"淄博":1,"连云港":1,"南京":1,"济南":4,"金华":1,"营口":1,"河南":1},"ANTHOGENOL":{"洛阳":1,"福州":1,"杭州":1,"温州":2,"营口":1,"茂名":1,"太原":2,"上海":3,"北京":1,"河南":1,"柳州":1,"成都":1,"昆明":1},"JEMA":{"洛阳":4,"北京":15,"苏州":9,"广州":2,"泰州":2,"绍兴":3,"金华":8,"湖州":2,"东莞":3,"泸州":2,"上海":9,"宁波":4,"德州":2,"合肥":2,"云南":3,"长沙":4,"台州":2,"珠海":2,"沧州":2,"天津":1,"杭州":11,"保定":2,"郑州":2,"梅州":2,"南京":2,"武汉":7,"吴江":1,"三门峡":2,"玉溪":1,"广西":10,"兰州":2,"济宁":2,"温州":1,"中山":1,"舟山":1,"深圳":1,"成都":3,"青岛":2,"福州":1,"佛山":1,"惠州":1,"河南":4,"西安":2,"淮安":3,"汕头":1,"潍坊":1,"济南":1,"南通":1,"衡水":1,"大同":2,"常熟":1,"吉林":1},"EAORON":{"洛阳":1,"宁波":23,"苏州":5,"镇江":5,"广州":10,"青岛":11,"温州":13,"绍兴":6,"天津":7,"杭州":23,"成都":6,"金华":7,"泉州":11,"太原":3,"无锡":3,"西安":7,"上海":26,"秦皇岛":3,"北京":18,"河南":7,"长沙":4,"珠海":2,"淄博":1,"焦作":1,"湖州":2,"佛山":2,"东莞":2,"惠州":3,"乌鲁木齐":4,"南京":7,"重庆":9,"郑州":1,"武汉":10,"丹东":1,"呼和浩特":3,"德州":5,"义乌":2,"台州":2,"肇庆":1,"银川":1,"昆明":1,"抚顺":1,"唐山":1,"营口":1,"三门峡":3,"福州":4,"云南":5,"昆山":3,"吉林":2,"南通":1,"深圳":4,"江门":1,"哈尔滨":2,"廊坊":1,"济南":1,"宜兴":2,"汕头":1,"合肥":1,"常熟":11,"南宁":1,"大连":2,"中山":2,"德阳":1,"大同":3,"连云港":3,"保定":1,"衡水":1,"沧州":1,"嘉兴":1,"厦门":4,"吴江":1},"SYRENE":{"洛阳":2,"苏州":5,"兰州":2,"广州":11,"武汉":2,"北京":17,"长沙":5,"嘉兴":6,"重庆":4,"无锡":7,"上海":22,"昆明":5,"吉林":4,"成都":10,"南京":2,"河南":3,"云南":2,"金华":5,"盘锦":1,"杭州":7,"芜湖":2,"常州":2,"承德":1,"淮安":1,"马鞍山":2,"汕尾":1,"天津":4,"淄博":3,"宁波":3,"镇江":2,"郑州":8,"中山":4,"舟山":1,"临沂":1,"大连":3,"扬州":2,"西安":2,"青岛":2,"哈尔滨":1,"温州":4,"汕头":1,"南昌":1,"南通":2,"大同":7,"吴江":1,"珠海":3,"南宁":1,"常德":1,"济南":2,"湖州":1,"昆山":1,"泉州":1,"义乌":1,"深圳":1,"福州":1,"佛山":2,"邢台":1,"邯郸":2,"张家界":1,"沧州":1,"合肥":1,"潍坊":1,"东莞":1,"临汾":1,"宝鸡":1,"开封":1,"绍兴":1,"连云港":1,"秦皇岛":1,"石家庄":1,"太原":5},"TRILOGY":{"深圳":7,"丹东":1,"淄博":1,"重庆":1,"北京":13,"广州":12,"苏州":7,"温州":4,"盐城":2,"湖州":5,"济南":3,"丽水":1,"桂林":1,"杭州":13,"青岛":3,"吴江":4,"株洲":2,"宁波":8,"上海":12,"廊坊":1,"德州":5,"昆明":1,"石家庄":1,"江门":1,"德阳":2,"南通":4,"武汉":4,"中山":5,"无锡":3,"东莞":4,"邢台":2,"广西":3,"茂名":32,"抚顺":3,"珠海":2,"天津":1,"芜湖":5,"长沙":8,"潍坊":2,"洛阳":2,"金华":2,"台州":5,"扬州":2,"贵阳":5,"连云港":3,"常德":1,"西安":1,"河南":2,"湘潭":1,"三门峡":1,"成都":2,"邯郸":2,"绍兴":5,"济宁":4,"乌鲁木齐":3,"大连":1,"保定":2,"荆州":1,"马鞍山":1,"哈尔滨":4,"大同":3,"呼和浩特":2,"宜兴":4,"义乌":1,"合肥":1,"汕头":1,"泸州":2,"衡水":1,"宜昌":1,"淮安":1,"揭阳":1,"佛山":3,"南充":1,"沧州":2,"常熟":2,"常州":1},"MENEVIT":{"深圳":1,"苏州":1,"北京":2,"汕头":1,"昆明":1,"温州":1,"烟台":1,"重庆":1,"东莞":1},"BIO-OIL":{"深圳":1,"绍兴":2,"重庆":1,"上海":1,"长沙":1,"成都":1,"西安":1,"盐城":1,"平顶山":1,"南京":2,"无锡":2,"苏州":1,"乌鲁木齐":1,"佛山":1},"UNICHI FORTY FATHOMS":{"遵义":1,"泰州":2,"吉林":3,"广西":2,"河南":6,"太仓":1,"连云港":3,"泸州":1,"重庆":2,"广州":7,"上海":5,"南京":5,"北京":10,"宁波":4,"武汉":8,"深圳":4,"无锡":4,"杭州":18,"芜湖":1,"金华":3,"淮安":1,"绍兴":4,"兰州":2,"郑州":2,"潍坊":1,"茂名":1,"揭阳":3,"洛阳":1,"营口":2,"青岛":1,"哈尔滨":2,"成都":6,"沈阳":2,"惠州":3,"嘉兴":3,"昆明":4,"鄂尔多斯":1,"云南":1,"宜兴":1,"长沙":8,"西安":2,"湖州":7,"呼和浩特":1,"温州":6,"抚顺":1,"大同":2,"常德":2,"南通":1,"衡水":2,"常州":1,"廊坊":1,"台州":1,"淄博":1,"佛山":2,"扬州":1,"中山":2,"石家庄":1,"鞍山":1},"BIOISLAND":{"连云港":7,"洛阳":13,"杭州":33,"绍兴":32,"重庆":7,"南充":4,"成都":21,"兰州":3,"中山":6,"天津":4,"淄博":2,"河南":11,"福州":8,"盐城":2,"昆明":6,"苏州":6,"深圳":12,"丽水":5,"湖州":11,"镇江":16,"武汉":7,"台州":7,"广西":45,"呼和浩特":1,"桂林":3,"广州":11,"青岛":2,"佛山":5,"上海":13,"昆山":4,"舟山":3,"温州":15,"惠州":1,"长沙":14,"廊坊":5,"德州":4,"营口":2,"北京":18,"宁波":10,"莱芜":1,"揭阳":6,"常州":1,"太仓":4,"义乌":3,"鞍山":5,"常德":3,"寿光":8,"乌鲁木齐":2,"郑州":1,"嘉兴":5,"吴江":1,"西安":10,"潮州":1,"厦门":3,"宜兴":1,"荆州":4,"菏泽":3,"云南":4,"沈阳":6,"泸州":1,"无锡":1,"长春":3,"聊城":3,"扬州":3,"东莞":1,"库尔勒":6,"马鞍山":2,"汕头":1,"烟台":1,"大连":1,"常熟":3,"沧州":5,"金华":2,"湛江":1,"潍坊":1,"临汾":1,"德阳":3,"开封":1,"贵阳":2,"哈尔滨":6,"肇庆":3,"张家口":2,"河源":1,"大同":1,"清远":4},"HEALTHY CARE":{"南昌":1,"太仓":2,"广州":8,"深圳":1,"福州":1,"北京":9,"南京":13,"绍兴":3,"湖州":2,"长沙":1,"石家庄":1,"宜兴":3,"海口":1,"珠海":1,"无锡":1,"西安":11,"佛山":1,"茂名":1,"三门峡":2,"洛阳":3,"惠州":1,"哈尔滨":2,"成都":4,"泸州":3,"贵阳":7,"昆明":1,"常德":3,"乌鲁木齐":2,"银川":3,"廊坊":1,"德州":2,"郑州":1,"苏州":2,"上海":5,"临沂":1,"太原":1,"济宁":3,"武汉":2,"烟台":4,"广西":7,"沈阳":1,"大同":4,"昆山":2,"义乌":1,"河南":2,"金华":2,"柳州":1,"吉林":1,"云南":1,"杭州":1,"常熟":1,"中山":2,"南通":1,"温州":1,"嘉兴":1},"GOODHEALTH":{"天津":5,"太仓":1,"重庆":10,"沧州":1,"成都":10,"佛山":1,"广州":1,"昆山":1,"温州":1,"北京":1,"廊坊":4,"哈尔滨":1,"江阴":5,"宁波":1,"杭州":1,"宜兴":1,"上海":6,"南昌":1,"保定":1,"广西":2,"宝鸡":6,"洛阳":2,"临沂":1,"沈阳":2,"西安":2,"揭阳":3,"云南":1,"德州":1,"深圳":1,"呼和浩特":3,"三门峡":4},"BLACKMORES":{"台州":4,"北京":19,"吉林":3,"营口":8,"宁波":10,"绍兴":8,"盐城":6,"义乌":2,"深圳":3,"重庆":17,"上海":18,"苏州":6,"杭州":18,"潮州":4,"西安":39,"南通":1,"焦作":4,"成都":17,"湖州":12,"鞍山":2,"潍坊":2,"马鞍山":1,"洛阳":6,"海口":3,"青岛":4,"泸州":4,"长沙":4,"德州":5,"郑州":15,"宜兴":3,"保定":3,"镇江":6,"武汉":7,"哈尔滨":5,"太原":1,"广州":9,"河南":11,"嘉兴":9,"温州":9,"昆明":14,"东莞":1,"咸阳":3,"南京":7,"葫芦岛":1,"无锡":2,"广西":2,"安阳":2,"廊坊":6,"大连":16,"滨州":1,"沈阳":2,"德阳":1,"枣庄":1,"大同":1,"中山":1,"汕头":1,"舟山":1,"开封":3,"库尔勒":2,"乌鲁木齐":1,"金华":2,"烟台":1,"株洲":1,"天津":5,"佛山":3,"厦门":1,"揭阳":2,"江阴":3,"吴江":1,"泉州":2,"衡水":1,"云南":1,"常熟":1,"扬州":1,"石家庄":1,"徐州":1,"福州":3,"济宁":1,"丹东":1},"REDWIN":{"丹东":1,"焦作":1,"洛阳":1,"杭州":2,"台州":1,"重庆":3,"上海":4,"广州":1,"南京":1,"兰州":1,"镇江":1,"北京":6,"马鞍山":1,"鄂尔多斯":1,"滨州":1,"无锡":3,"深圳":4,"长沙":1,"河南":2,"桂林":1,"连云港":2,"温州":16,"嘉兴":1,"郑州":1,"宁波":1,"曲靖":1,"武汉":1,"苏州":1,"湖州":1,"枣庄":1,"哈尔滨":2,"惠州":1,"绍兴":3,"合肥":1,"济南":2,"德阳":1,"青岛":5,"淄博":1,"泉州":1,"中山":1,"江阴":1,"成都":3,"宜昌":1,"昆明":1},"COMVITA":{"丹东":1,"天津":1,"温州":9,"北京":2,"上海":8,"齐齐哈尔":6,"成都":4,"滨州":2,"宁波":2,"南京":2,"枣庄":1,"沈阳":1,"深圳":4,"兰州":9,"南昌":1,"平顶山":2,"江阴":2,"武汉":1,"济南":3,"重庆":21,"河南":1,"嘉兴":3,"义乌":2,"大连":24,"青岛":3,"广州":3,"丽水":1,"太原":1,"常熟":3,"苏州":2,"镇江":1,"杭州":6,"绍兴":1,"江门":1,"惠州":1,"宜兴":1,"大庆":1,"无锡":2,"长春":1,"德阳":1,"湛江":2,"三门峡":1,"临汾":1,"保定":1,"廊坊":1},"PEARL DROPS":{"丹东":1,"河南":3,"北京":4,"重庆":1,"温州":2,"武汉":1,"杭州":1,"枣庄":1,"广州":4,"上海":3,"济南":1,"宁波":1,"常德":1},"SAVAR":{"泰州":4,"汕头":2,"北京":25,"珠海":5,"青岛":4,"绍兴":6,"深圳":8,"鞍山":3,"寿光":2,"苏州":13,"温州":13,"江阴":4,"三门峡":2,"岳阳":2,"宁波":12,"德阳":4,"大连":4,"盐城":3,"杭州":24,"成都":6,"大同":2,"上海":20,"潍坊":2,"茂名":1,"长沙":5,"宜兴":1,"武汉":3,"佛山":3,"兰州":1,"莱芜":1,"惠州":1,"扬州":2,"银川":1,"库尔勒":4,"宿迁":3,"枣庄":2,"南京":4,"鄂尔多斯":1,"衡水":4,"金华":2,"河南":9,"重庆":1,"常熟":4,"洛阳":3,"沈阳":11,"芜湖":2,"哈尔滨":9,"济南":3,"广州":5,"长春":3,"常德":1,"湛江":1,"台州":1,"广西":1,"泉州":1,"邯郸":2,"湖州":5,"德州":3,"抚顺":1,"乌鲁木齐":4,"郑州":1,"西安":3,"金坛":3,"东莞":1,"义乌":1,"昆明":1,"镇江":1,"嘉兴":3,"石家庄":1,"无锡":3,"海门":1,"马鞍山":1,"淮安":1,"湘潭":1,"淄博":1,"沧州":1,"天津":1,"南通":1,"吴江":1},"GOAT SOAP":{"武汉":7,"湘潭":6,"杭州":5,"昆明":3,"宁波":20,"中山":2,"保定":1,"长沙":1,"上海":8,"镇江":8,"北京":17,"广州":7,"重庆":1,"丽水":1,"苏州":1,"珠海":1,"成都":5,"沈阳":1,"绍兴":6,"南京":5,"滨州":1,"芜湖":1,"西安":2,"温州":2,"太原":2,"渭南":1,"河南":2,"张家界":2,"湖州":3,"洛阳":2,"嘉兴":1,"郑州":1,"衡水":1,"佛山":2,"义乌":1,"宜兴":1,"云南":2,"常州":3},"NORDIC NATURALS":{"湛江":2,"洛阳":1,"杭州":5,"湖州":3,"南京":1,"常德":1,"温州":7,"上海":3,"长沙":2,"武汉":2,"北京":1,"镇江":3,"宁波":1,"河南":1,"重庆":3,"江门":1,"西安":1,"泉州":1,"天津":1,"成都":1,"汕头":2,"义乌":1,"乌鲁木齐":2,"大连":1,"丽水":1,"广州":1,"保定":1},"ELEVIT":{"湛江":2,"北京":5,"苏州":1,"杭州":3,"常德":1,"绍兴":3,"惠州":1,"湖州":1,"昆明":2,"温州":2,"上海":1,"武汉":1,"嘉兴":1,"成都":2,"宜兴":1,"贵阳":1,"张家口":1,"烟台":1,"泉州":1,"揭阳":1,"东莞":1,"大庆":2},"MAXIGENES":{"淄博":1,"广州":4,"成都":2,"上海":5,"镇江":1,"长沙":1,"揭阳":1,"杭州":2,"三门峡":1,"荆州":1,"吴江":1,"绍兴":3,"惠州":1,"汕头":2,"湖州":1,"湛江":1,"河南":3,"北京":1,"台州":1,"青岛":1,"云南":1},"MILK & CO":{"河南":2,"北京":4,"乌鲁木齐":2,"沈阳":3,"青岛":3,"上海":7,"温州":4,"广州":8,"杭州":14,"重庆":3,"湖州":6,"昆明":3,"嘉兴":1,"株洲":2,"宁波":3,"深圳":4,"佛山":4,"廊坊":1,"石家庄":2,"南宁":2,"金华":1,"天津":4,"南京":3,"丽水":2,"成都":2,"济南":3,"惠州":1,"聊城":1,"昆山":4,"武汉":3,"哈尔滨":2,"郑州":1,"台州":4,"绍兴":6,"长沙":5,"银川":2,"芜湖":2,"荆州":1,"汕头":2,"克拉玛依":1,"宜兴":1,"吉林":1,"合肥":4,"大同":1,"苏州":2,"镇江":1,"淮安":1,"南充":1,"常德":1,"南昌":1,"盐城":1,"西安":1},"GRIN":{"河南":8,"杭州":3,"上海":2,"福州":1,"温州":6,"宁波":3,"北京":5,"成都":1,"义乌":1,"乌鲁木齐":1,"绍兴":2,"石家庄":1,"邯郸":1,"金华":2},"THURSDAY":{"河南":2,"深圳":1,"济南":1,"宁波":1,"无锡":2,"北京":1,"温州":3,"盘锦":1,"德州":1,"上海":1,"青岛":1,"天津":1,"玉溪":1,"宜昌":1,"武汉":1},"FEMFRESH":{"苏州":3,"焦作":1,"重庆":3,"无锡":3,"深圳":7,"南通":4,"沈阳":1,"北京":6,"徐州":1,"镇江":5,"佛山":2,"温州":2,"义乌":2,"武汉":1,"洛阳":11,"天津":1,"杭州":10,"广西":1,"泰州":1,"西安":2,"常州":1,"济南":1,"吴江":1,"嘉兴":1,"玉溪":1,"合肥":1,"台州":1,"上海":10,"潍坊":1,"宁波":2,"河南":2,"潮州":1,"延安":1,"江门":1,"保定":1,"青岛":5,"宜昌":1,"湖州":1,"廊坊":1,"金坛":2,"郑州":1,"绍兴":3,"盐城":2,"济宁":1,"哈尔滨":2,"汕头":1,"宜兴":1,"金华":1,"中山":2,"茂名":2,"乌鲁木齐":3,"大同":2,"南京":2,"扬州":2,"宿迁":1,"邯郸":1,"德州":3,"成都":1,"石家庄":1},"MUNCHIKIN":{"邢台":1,"莱芜":1,"成都":1,"德州":1,"上海":1,"绍兴":1,"杭州":2,"北京":2,"廊坊":1},"JELLYCAT":{"邢台":1,"成都":3,"洛阳":1,"太仓":1,"重庆":1,"常德":1,"湖州":2,"无锡":2,"莱芜":1,"中山":1,"长沙":4,"临汾":2,"金华":1,"广州":5,"杭州":11,"泸州":2,"温州":3,"北海":1,"库尔勒":2,"宜兴":2,"绍兴":4,"上海":5,"廊坊":2,"沧州":1,"沈阳":3,"芜湖":2,"天津":2,"深圳":2,"武汉":2,"苏州":4,"佛山":5,"大连":2,"哈尔滨":7,"济南":1,"青岛":1,"金坛":1,"丽水":1,"北京":4,"乌鲁木齐":1,"珠海":1,"泉州":2,"常熟":1,"大同":1,"福州":1,"嘉兴":1,"河南":1},"OASIS BEAUTY":{"天津":1,"杭州":1,"上海":2,"无锡":1,"南京":1},"LACUES":{"义乌":1,"武汉":1,"湖州":1,"成都":1,"上海":1,"丽水":1},"ANTIPODES":{"义乌":2,"昆明":3,"北京":13,"长沙":7,"青岛":6,"上海":35,"广州":13,"郑州":7,"无锡":16,"重庆":11,"杭州":15,"柳州":1,"嘉兴":3,"珠海":3,"成都":23,"洛阳":6,"三门峡":2,"湖州":7,"株洲":2,"盘锦":2,"包头":6,"德州":4,"北海":2,"南宁":2,"枣庄":2,"东莞":1,"烟台":4,"邢台":2,"河南":8,"广西":6,"宁波":2,"盐城":4,"嘉峪关":2,"淄博":2,"苏州":9,"福州":1,"潍坊":2,"揭阳":6,"诸暨":1,"深圳":10,"连云港":1,"太原":1,"沧州":2,"马鞍山":4,"西安":2,"中山":1,"九江":1,"兰州":1,"湘潭":1,"温州":13,"绍兴":7,"天津":2,"玉溪":1,"肇庆":1,"武汉":7,"梅州":1,"济南":3,"厦门":1,"吴江":1,"惠州":2,"乌鲁木齐":1,"常州":1,"保定":1,"金华":1,"南京":1,"哈尔滨":2,"镇江":2,"汕头":1,"大同":2,"廊坊":1,"衡水":1,"扬州":4,"大连":2,"宜兴":2,"佛山":4,"吉林":1,"银川":1,"常熟":3,"沈阳":2,"临沂":1,"台州":2,"鞍山":1,"芜湖":1,"泸州":1,"常德":1,"呼和浩特":1},"PARRS":{"焦作":1,"济南":1,"杭州":9,"佛山":4,"长沙":7,"上海":10,"西安":1,"深圳":1,"济宁":2,"北京":3,"绍兴":2,"宝鸡":2,"武汉":2,"无锡":1,"成都":1,"吉林":2,"柳州":1,"昆山":1,"河南":3,"天津":2,"嘉兴":1,"广州":1,"温州":1,"南昌":2,"大庆":2,"台州":2},"METAMUCIL":{"杭州":8,"广州":3,"无锡":1,"台州":5,"深圳":1,"上海":6,"海口":1,"烟台":1,"北京":2,"云南":1,"长沙":1,"重庆":2,"金华":2,"河南":1,"常熟":1,"绍兴":2,"哈尔滨":1,"义乌":1,"淄博":1,"常德":1,"青岛":1,"德州":1,"大连":2},"FLORADIX":{"邢台":1,"成都":1,"贵阳":2,"河南":4,"盐城":3,"大连":1,"营口":5,"杭州":7,"哈尔滨":1,"北京":5,"长沙":3,"泸州":2,"宁波":2,"洛阳":2,"廊坊":2,"台州":3,"连云港":1,"沈阳":1,"广州":3,"嘉兴":1,"西安":1,"温州":5,"厦门":2,"滨州":2,"临沂":1,"中山":2,"苏州":3,"揭阳":1,"汕头":1,"无锡":2,"佛山":1,"天津":2,"昆山":1,"郑州":1,"上海":2,"武汉":2,"深圳":1,"徐州":1,"泉州":1,"湖州":1},"OSTELIN":{"西安":8,"中山":14,"淄博":2,"杭州":25,"乌鲁木齐":3,"上海":21,"洛阳":9,"温州":24,"镇江":5,"成都":11,"河南":10,"湖州":12,"绍兴":14,"广州":15,"北京":7,"库尔勒":2,"合肥":6,"泸州":2,"德州":3,"长沙":1,"潮州":2,"舟山":3,"沈阳":1,"梅州":2,"武汉":3,"济南":1,"吴江":1,"太仓":1,"焦作":1,"深圳":6,"兰州":3,"重庆":24,"衡水":1,"临沂":3,"昆明":5,"唐山":3,"湛江":2,"嘉兴":4,"三门峡":1,"青岛":3,"常德":6,"汕头":1,"泉州":1,"南京":3,"金华":2,"台州":3,"宁波":2,"哈尔滨":1,"沧州":2,"吉林":2,"昆山":3,"福州":1,"德阳":2,"保定":1,"惠州":1,"大同":2},"ECOROA":{"西安":1},"U BY KOTEX":{"深圳":1,"北京":3,"镇江":2,"杭州":1,"绍兴":2,"广州":1,"淄博":1,"天津":1,"义乌":9,"长沙":2,"丽水":3,"上海":5,"衡水":2,"苏州":2,"无锡":2,"河南":3,"大同":1},"KIWIHERB":{"深圳":2,"北京":2,"上海":7,"盘锦":1,"温州":2,"绍兴":6,"盐城":1,"沧州":4,"宜兴":2,"株洲":1,"马鞍山":1,"沈阳":3,"广州":2,"无锡":4,"成都":7,"广西":5,"德阳":2,"中山":3,"临汾":1,"宁波":1,"连云港":2,"库尔勒":1,"吴江":2,"洛阳":1,"荆州":1,"邯郸":1,"聊城":2,"珠海":1,"河南":2},"SKINNIES":{"深圳":1,"镇江":2,"北京":1,"乌鲁木齐":1,"杭州":2,"丽水":1,"茂名":5,"宜兴":1,"沈阳":2,"重庆":1,"温州":1,"珠海":1,"福州":1},"TRIUMPH N DISASTER":{"株洲":1,"宁波":1,"哈尔滨":1,"郑州":2,"长春":1,"汕头":1,"北京":2,"廊坊":2,"潍坊":3,"上海":1,"杭州":1,"佛山":2,"大连":1,"玉溪":2,"深圳":2,"兰州":2,"合肥":1,"武汉":1,"三亚":2,"丹东":1,"盐城":1,"嘉兴":1,"无锡":1,"河南":1,"湛江":2,"大同":1},"GM":{"广西":20,"连云港":1,"绍兴":47,"杭州":17,"苏州":2,"珠海":2,"台州":1,"上海":6,"芜湖":1,"保定":1,"成都":1,"长沙":5,"德州":16,"北京":4,"揭阳":3,"佛山":2,"洛阳":1,"郑州":4,"廊坊":2,"哈尔滨":1,"宁波":1,"南充":1,"常州":1,"广州":6,"徐州":1,"温州":2,"昆山":2,"太原":1,"湖州":3,"汕头":2,"河南":1,"常熟":4,"大连":1,"湘潭":2,"深圳":1,"宜兴":3,"扬州":1,"武汉":1,"济南":1,"中山":3,"衡水":2,"大同":1,"诸暨":4,"金坛":1},"DERMATIX":{"济南":2,"成都":4,"南京":1,"绍兴":3,"德州":1,"北京":2,"南昌":2,"乌鲁木齐":1,"温州":1,"重庆":2,"宁波":2},"FREEZEFRAME":{"太仓":1,"嘉兴":4,"上海":4,"泸州":1,"杭州":3,"无锡":2,"西安":8,"淄博":6,"深圳":2,"汕尾":1,"济南":2,"连云港":2,"廊坊":1,"东莞":1,"金华":1,"德州":2,"广州":4,"惠州":3,"鄂尔多斯":1,"长春":1,"重庆":1,"北京":5,"湖州":1,"潮州":1,"青岛":1,"河南":2,"沈阳":1,"石家庄":1,"南京":1,"哈尔滨":1,"大连":1,"长沙":1,"武汉":2,"常德":1,"宁波":3,"丽水":1},"KIWIGARDEN":{"太仓":3,"杭州":3,"北京":2,"温州":2,"武汉":2,"荆州":1,"诸暨":2,"淄博":1,"吉林":1,"绍兴":2,"佛山":2,"长沙":1,"沧州":2,"广州":1,"泉州":3,"湛江":4,"常德":1,"汕头":2,"韶关":1},"PRO-LIFE":{"绍兴":1,"台州":1,"杭州":5,"重庆":1,"昆明":3,"北京":2,"成都":1,"抚顺":1,"南京":1,"沧州":1,"无锡":1,"肇庆":1},"NATURES WAY":{"绍兴":8,"保定":1,"杭州":6,"湖州":3,"重庆":2,"泰安":2,"上海":8,"盐城":1,"北京":1,"丽水":1,"成都":2,"广州":9,"武汉":2,"河南":3,"温州":5,"佛山":4,"嘉兴":1,"广西":7,"宁波":1,"西安":2,"韶关":5},"BRITA":{"石家庄":1},"LINDEN LEAVES":{"太仓":1,"苏州":1,"西安":2,"贵阳":1,"抚顺":1,"广西":1,"佛山":1,"广州":3,"天津":1,"云南":1,"淄博":1,"常州":3,"长沙":1,"温州":1,"上海":1,"大连":1},"FICCECODE":{"昆明":4,"广州":10,"绍兴":1,"青岛":1,"重庆":2,"太原":1,"成都":6,"舟山":1,"北京":7,"天津":4,"江阴":2,"上海":4,"温州":7,"福州":2,"大连":1,"洛阳":4,"武汉":4,"苏州":8,"淄博":2,"中山":3,"开封":1,"保定":2,"杭州":4,"茂名":2,"广西":1,"西安":4,"淮安":3,"济南":1,"库尔勒":2,"平顶山":2,"芜湖":2,"常熟":1,"无锡":1,"哈尔滨":5,"河南":3,"湖州":2,"长沙":3,"金华":1,"石家庄":1,"宁波":1,"佛山":1,"嘉兴":1,"义乌":1},"CLINICIANS":{"烟台":3,"肇庆":3,"沧州":4,"北京":8,"镇江":1,"广州":16,"天津":8,"绍兴":9,"上海":14,"成都":4,"廊坊":1,"深圳":12,"中山":5,"江门":5,"海口":2,"佛山":4,"义乌":9,"长沙":2,"珠海":1,"金坛":4,"长春":3,"洛阳":4,"东莞":2,"苏州":5,"保定":6,"扬州":2,"乌鲁木齐":3,"盐城":4,"青岛":2,"西安":2,"沈阳":3,"吉林":3,"杭州":7,"南京":4,"云南":2,"银川":1,"哈尔滨":5,"昆山":3,"常州":1,"无锡":1,"昆明":5,"湘潭":2,"荆州":1,"河源":1,"厦门":1,"湖州":1,"泉州":1,"太仓":1,"邯郸":1,"石家庄":2,"温州":6},"HOLISTIC HAIR":{"广州":3,"泉州":3,"青岛":3,"大连":1,"乌鲁木齐":3,"绍兴":3,"长沙":10,"武汉":1,"上海":7,"南京":3,"杭州":1,"丽水":2,"昆明":2,"河南":1,"泸州":1,"宜兴":2,"苏州":5,"无锡":2,"佛山":2,"汕头":1,"广西":1,"成都":3,"济南":4,"北京":1,"常熟":1,"大同":2,"衡水":2,"江阴":2},"SUNSWEET":{"济南":1,"南通":1,"上海":1,"长春":1,"北京":3,"乌鲁木齐":1,"天津":1,"苏州":1,"太原":1,"珠海":1,"常德":1,"青岛":1},"ORAL-B":{"昆明":2,"中山":1,"温州":1,"三门峡":4,"上海":4,"杭州":4,"佛山":3,"汕头":2,"淮安":1,"惠州":1,"成都":1,"天津":1,"嘉兴":2,"常熟":1,"昆山":2,"宁波":1,"北京":2,"无锡":1},"THOMPSON'S":{"成都":3,"烟台":1,"苏州":2,"湛江":1,"福州":2,"廊坊":2,"杭州":1,"河源":2,"金华":2,"西安":6},"ECOSTORE":{"温州":13,"珠海":1,"保定":1,"上海":3,"杭州":16,"成都":4,"天津":5,"北京":6,"深圳":2,"苏州":15,"绍兴":2,"乌鲁木齐":1,"广州":3,"西安":3,"无锡":4,"河南":5,"青岛":3,"烟台":1,"银川":2,"茂名":9,"湖州":11,"南充":1,"诸暨":1,"太原":2,"惠州":1,"蓬莱":1,"丽水":1,"常州":1,"广西":3,"宁波":6,"临汾":2,"嘉兴":7,"开封":1,"佛山":2,"宜兴":1,"江阴":2,"长沙":1,"厦门":1,"常德":1,"武汉":1,"福州":1,"衡水":1,"洛阳":1},"CHILDLIFE":{"杭州":5,"苏州":1,"绍兴":4,"天津":2,"长沙":5,"海口":1,"温州":1,"河南":1,"宁波":2,"合肥":1,"昆明":1,"德州":2,"上海":5,"成都":2,"北京":1,"烟台":1,"金华":1,"淄博":1,"青岛":1,"湖州":3,"聊城":2,"常熟":1,"唐山":1,"广西":2},"EASIYO":{"常德":4,"嘉兴":1,"广州":2,"珠海":3,"深圳":1},"HARKER":{"杭州":4,"深圳":1,"成都":7,"温州":2,"乌鲁木齐":3},"ROYAL NECTAR":{"营口":5,"重庆":11,"金华":1,"济南":2,"昆明":1,"潮州":4,"上海":11,"珠海":2,"合肥":2,"福州":1,"茂名":2,"长春":2,"成都":5,"镇江":2,"淄博":1,"北京":9,"云南":1,"哈尔滨":3,"海口":1,"石家庄":1,"河南":1,"德州":1,"佛山":1,"南京":1,"武汉":2,"广西":1,"宜兴":1,"长沙":2,"中山":1,"嘉兴":1,"常熟":1},"DISCREET":{"宁波":1,"贵阳":1,"南京":1,"杭州":1,"重庆":7,"成都":6,"上海":2,"齐齐哈尔":1,"北京":3,"烟台":1,"大同":1},"PROCTOSEDYL":{"宁波":2,"杭州":1,"哈尔滨":1,"洛阳":1,"深圳":1},"OGX":{"宁波":2},"BIOGLAN":{"苏州":1},"NUTRALIFE":{"厦门":5,"九江":2,"成都":6,"杭州":1,"大同":1,"宁波":1,"武汉":3,"淄博":1,"丽水":0,"上海":1},"KARICARE":{"湖州":5,"杭州":8,"佛山":7,"温州":3,"嘉兴":2,"枣庄":3,"上海":23,"宜兴":2,"临汾":1,"河源":3,"滨州":1,"广州":1,"聊城":1},"HEALTHERIES":{"广州":5,"苏州":1,"佛山":2,"连云港":1,"西安":2,"昆明":1,"温州":7,"成都":8,"北京":2,"潮州":1,"无锡":1,"惠州":1,"青岛":1,"镇江":6,"枣庄":1,"淄博":2,"常熟":1,"贵阳":1,"常州":1,"营口":2},"MRS ROGERS":{"青岛":1,"杭州":4,"重庆":6,"义乌":5,"广州":9,"枣庄":4,"太仓":6,"金坛":4,"上海":2,"苏州":3,"哈尔滨":1,"沧州":1,"葫芦岛":2,"保定":2,"宜兴":1,"绍兴":1,"吴江":1,"金华":2,"湖州":4,"乌鲁木齐":1,"阳江":1,"河南":2,"北京":2,"吉林":3,"温州":2,"库尔勒":2,"石家庄":1,"济南":1,"宝鸡":2,"南通":2,"丽水":1,"大同":2,"茂名":1,"广西":1,"嘉兴":1,"深圳":2},"WEET-BIX":{"南通":2,"西安":1,"青岛":1,"北京":4,"焦作":1,"河南":2,"上海":2,"嘉兴":1,"昆明":4,"宁波":1,"合肥":1,"中山":3,"滨州":1,"温州":1,"武汉":1,"保定":1,"镇江":1,"苏州":2,"连云港":1,"丽水":2,"惠州":1,"无锡":2,"长沙":1,"深圳":1,"湖州":1,"济南":1,"哈尔滨":1,"成都":1},"JOJOBA":{"天津":1,"合肥":1,"桂林":1},"AVEENO":{"宁波":2,"绍兴":1,"中山":1,"嘉兴":4,"杭州":14,"无锡":4,"江阴":9,"汕头":1,"济南":2,"芜湖":1,"菏泽":1,"吴江":4,"金华":2,"南充":1,"呼和浩特":1,"北京":1,"乌鲁木齐":1,"沈阳":1,"扬州":4,"宜兴":3,"上海":1,"云南":1,"盘锦":2,"宝鸡":4,"常熟":8,"西安":4,"广州":2},"OASIS SUN":{"深圳":1,"北京":4,"上海":2,"重庆":1,"乌鲁木齐":1,"吉林":3,"中山":1,"湛江":1,"云南":1,"杭州":3,"清远":3,"大连":1,"克拉玛依":1,"长沙":1,"衡水":1,"宜兴":1,"哈尔滨":1,"绍兴":1,"常德":1},"EQUAZEN":{"贵阳":3,"枣庄":1,"长春":1,"北京":3},"NU-LAX":{"无锡":3,"天津":2,"杭州":5,"成都":2,"沈阳":1,"哈尔滨":3,"泉州":1,"重庆":2,"河源":1,"金华":1,"太原":1,"大连":1,"中山":1},"LAMISIL":{"牡丹江":5,"北京":1,"镇江":3,"温州":1,"上海":1,"河南":1,"成都":1},"SAVARSAMPLE":{"青岛":5,"德阳":5,"绍兴":1,"广州":6,"上海":5,"丹东":5},"GOLD KIWI":{"绍兴":1,"杭州":1,"舟山":18,"上海":2,"郑州":2,"河南":1,"洛阳":2,"江阴":4,"天津":1,"阳泉":2},"YPL":{"杭州":6,"北京":10,"上海":8,"南京":2,"绍兴":7,"丽水":3,"大同":3,"东莞":1,"江门":3,"中山":3,"佛山":5,"江阴":2,"银川":1,"宜兴":1,"茂名":2,"济南":6,"广西":2,"广州":4,"苏州":2,"保定":2,"无锡":4,"洛阳":1,"长沙":4,"温州":1,"成都":3,"天津":3,"沈阳":2,"吉林":1,"大连":1,"沧州":1,"金华":2,"合肥":1,"湖州":2,"云南":1,"汕头":1,"西安":1,"青岛":1,"淄博":1,"太仓":1},"F-1-3-2 BIOISLAND":{"丽水":2,"镇江":6,"温州":1,"杭州":4,"宁波":3,"兰州":1,"潮州":2,"常州":1,"鄂尔多斯":1,"寿光":2,"广州":7,"绍兴":1,"西安":2,"荆州":1,"北京":2,"聊城":1,"上海":5,"湛江":2,"东莞":1,"马鞍山":1,"重庆":4,"南宁":2},"OLIVIA":{"温州":3,"烟台":6,"昆山":1,"湖州":3,"杭州":2,"义乌":1,"绍兴":1,"泉州":1,"北京":1},"CENTRUM":{"湛江":1,"海口":1,"广西":5,"广州":1,"嘉兴":1,"邯郸":1,"台州":2,"杭州":1},"FAREX":{"湛江":3,"莱芜":3,"合肥":5,"武汉":8,"中山":3,"廊坊":1,"淄博":1,"西安":2,"温州":3,"河南":7,"绍兴":4,"德州":1,"北京":3,"佛山":1,"太仓":1,"成都":3,"石家庄":3,"连云港":2,"哈尔滨":2,"惠州":1},"DDMASK":{"天津":2,"杭州":2,"大连":2,"深圳":7,"台州":1,"福州":4,"上海":4,"德州":1,"常熟":1,"北京":2,"苏州":1},"GRAN'S REMEDY":{"北京":2,"衡水":1,"成都":1,"广州":1,"南京":1,"宁波":1,"上海":1},"FRESCO":{"武汉":1,"云南":1,"重庆":5,"苏州":3,"杭州":10,"成都":2,"义乌":1,"珠海":1,"常州":1},"EGO":{"湖州":7,"鞍山":1,"武汉":2,"镇江":2,"济宁":1,"杭州":28,"上海":13,"宁波":4,"深圳":3,"台州":1,"芜湖":1,"三门峡":1,"盐城":1,"营口":2,"沈阳":1,"泸州":2,"绍兴":6,"温州":12,"成都":8,"义乌":1,"广州":7,"无锡":3,"北京":5,"乌鲁木齐":3,"西安":2,"潮州":2,"大同":1,"宝鸡":1,"哈尔滨":2,"银川":1,"合肥":1,"开封":1,"荆州":1,"云南":2,"昆山":2,"湛江":1,"大连":1,"南京":2,"江阴":4,"常德":1,"苏州":2,"平顶山":1,"南通":1,"重庆":1,"廊坊":1,"中山":1,"佛山":1,"金坛":1,"蓬莱":1,"嘉兴":3,"丽水":4,"常熟":6,"天津":1,"长沙":2,"德阳":1,"青岛":2,"莱芜":1,"临汾":1,"广西":2},"EARTHWISE":{"盐城":2,"杭州":4,"宁波":1,"成都":3,"武汉":1,"保定":1,"马鞍山":2,"聊城":1,"银川":2,"温州":1,"肇庆":3,"南充":1,"湛江":1,"东莞":1,"太原":2,"昆山":3,"佛山":2,"广州":1,"天津":1},"LAXEASE":{"嘉兴":6,"江门":10,"湖州":1,"杭州":1,"重庆":1,"台州":1,"常熟":1,"哈尔滨":2},"AEROGARD":{"无锡":1,"杭州":1,"西安":2},"PIC'S":{"青岛":1},"B.BOX":{"河南":2,"莱芜":4,"合肥":1,"长沙":2,"南通":2,"北京":3,"临汾":3,"金华":2,"广州":11,"杭州":11,"呼和浩特":1,"泸州":1,"嘉兴":3,"天津":6,"宁波":1,"太仓":2,"常德":1,"库尔勒":3,"上海":7,"廊坊":6,"洛阳":3,"苏州":2,"绍兴":5,"温州":3,"成都":2,"滨州":2,"南京":3,"乌鲁木齐":1,"镇江":1,"青岛":3,"无锡":1,"诸暨":1,"汕头":1,"昆明":1,"中山":2,"哈尔滨":1,"惠州":2,"常熟":3,"荆州":1,"沈阳":2,"湖州":3,"宝鸡":4,"西安":2,"泉州":1,"聊城":1,"深圳":2},"STREAMLAND":{"泰州":2,"成都":4,"北京":6,"苏州":4,"西安":3,"青岛":1,"芜湖":1,"镇江":2,"吉林":2,"沈阳":3,"武汉":2,"温州":1,"常州":1,"江门":1,"广州":1,"常熟":2,"深圳":1,"绍兴":1,"昆明":1,"杭州":2,"淄博":1,"宝鸡":1},"RADIANCE":{"杭州":5,"上海":2,"长沙":11,"广州":3,"成都":3,"唐山":1,"南京":2,"三门峡":1,"湖州":1,"德阳":2,"绍兴":1,"西安":1,"深圳":2},"SMILE":{"成都":3,"广州":1,"舟山":1,"重庆":1,"北京":1,"天津":2,"上海":1},"SELSUN":{"北京":4,"台州":1,"宁波":1,"温州":10,"天津":2,"义乌":2,"绍兴":1,"广州":1,"深圳":1,"惠州":1,"杭州":1,"长沙":1},"SOULFUL":{"常德":1,"温州":2,"嘉兴":1,"西安":1,"常熟":1},"MORNING FRESH":{"温州":5,"宜兴":2,"海口":1,"上海":2,"北京":7,"成都":2,"嘉兴":4,"武汉":1,"重庆":1,"荆州":1,"开封":2,"济南":3,"湖州":1,"义乌":1,"杭州":2,"绍兴":2,"南京":1,"沧州":1,"河南":2,"天津":1,"大同":1,"丽水":5,"茂名":1,"沈阳":1,"莱芜":1,"常德":1,"石家庄":1,"佛山":2,"临汾":1,"苏州":1,"长沙":1},"DR.LEWINNS":{"天津":2,"鄂尔多斯":1,"清远":1,"河南":1,"深圳":1},"VIERRA":{"绍兴":9,"义乌":5,"河南":3,"深圳":2,"无锡":3,"温州":3,"太原":6,"南通":2,"台州":1,"上海":7,"佛山":1},"LANOCREME":{"济南":2,"洛阳":2,"泸州":1,"绍兴":1,"揭阳":1,"成都":1,"大同":1,"北京":1,"徐州":1,"温州":2,"嘉兴":1,"汕头":2,"丽水":2,"哈尔滨":1,"上海":1,"台州":3,"天津":1,"杭州":1,"常熟":2,"珠海":1,"临沂":1,"长沙":1,"金坛":1},"XHEKPON":{"湖州":3,"宁波":7,"连云港":2,"德州":2,"常德":2,"北京":5,"上海":12,"成都":7,"枣庄":1,"长沙":5,"佛山":3,"义乌":1,"南通":2,"杭州":5,"石家庄":1,"渭南":2,"扬州":1,"深圳":5,"长春":1,"江门":1,"芜湖":2,"泸州":1,"武汉":3,"桂林":1,"金华":1,"南京":2,"广州":3,"天津":2,"唐山":1,"绍兴":4,"重庆":3,"河南":3,"昆明":1,"青岛":1,"沈阳":1,"吴江":1,"哈尔滨":5,"郑州":1,"温州":2,"苏州":4,"昆山":1,"洛阳":1,"无锡":1,"镇江":1,"东莞":4,"常熟":3,"中山":1,"揭阳":1,"滨州":1,"嘉兴":1,"徐州":1,"西安":1,"福州":1,"丽水":1},"MTIOQ":{"广州":2,"西安":1,"包头":2,"宁波":2,"金坛":2,"苏州":2,"镇江":1,"长沙":2,"佛山":2,"银川":2,"台州":2,"上海":4,"中山":2,"成都":1,"吉林":2,"宜兴":1,"武汉":1},"PEPPA PIG":{"杭州":2,"中山":2,"宁波":1,"广州":1,"常德":4},"WILD FERNS":{"长沙":1,"无锡":1,"南京":1,"柳州":1,"德州":1},"OXYGEN":{"廊坊":2,"河南":2,"惠州":2,"抚顺":1,"台州":2,"北京":1,"济南":1,"乌鲁木齐":1,"中山":2,"德州":1,"天津":1,"杭州":3,"吉林":1,"成都":1,"重庆":1,"深圳":1},"THURSDAY PLANTATION":{"贵阳":1,"宁波":1,"淮安":2,"南京":1,"上海":3,"银川":1,"河南":1,"北京":4,"成都":4,"苏州":1,"开封":1,"江阴":6,"洛阳":3,"湘潭":1,"江门":1,"温州":1,"汕头":2,"杭州":1,"常熟":1},"MOROCCANOIL":{"大连":1,"深圳":1,"云南":1,"杭州":2,"长沙":2,"宜兴":1,"洛阳":1,"上海":2,"济宁":1,"北京":1,"长春":1,"连云港":1,"佛山":1,"丽水":1,"广西":1},"NUTRITION CARE":{"昆山":1,"海口":1,"兰州":2,"青岛":6,"江阴":6,"潮州":1,"河南":1,"无锡":1,"重庆":1,"太原":1,"广州":1,"宁波":1},"EDMONDS":{"佛山":2,"义乌":1,"吉林":1,"苏州":1},"MHD":{"福州":12,"温州":2,"义乌":1,"昆明":2,"佛山":1,"丽水":1,"西安":2,"长沙":1,"无锡":1},"NEW ZEAL":{"上海":2,"广州":2,"茂名":1,"烟台":1,"莱芜":1,"北京":7,"河南":3,"杭州":1,"成都":1,"无锡":1,"哈尔滨":1,"北海":1,"南京":3,"桂林":1,"青岛":3,"潍坊":1,"盘锦":1,"淮安":1,"镇江":2,"柳州":1,"渭南":1,"廊坊":1,"天津":1,"泰州":3},"SESDERMA":{"苏州":2,"玉溪":2,"杭州":3,"宁波":2,"绍兴":1,"南宁":3,"合肥":1,"北京":1,"中山":2,"广州":2,"福州":1,"温州":1},"CLAIROL":{"上海":3,"昆明":2,"淮安":2,"宁波":1,"佛山":1},"MUNCHKIN":{"西安":1,"洛阳":1,"泸州":1,"绍兴":1,"湖州":2,"上海":1,"芜湖":1,"北京":3,"青岛":1,"杭州":2,"惠州":1,"河南":1},"HEEL FAST":{"金坛":1,"河南":3,"泉州":1,"枣庄":1,"济南":1,"大连":1,"惠州":1,"西安":2,"昆山":1,"太原":1,"宁波":1,"天津":1,"德州":1,"湖州":1,"邯郸":1,"上海":5,"珠海":1,"广州":1,"杭州":4,"成都":2,"无锡":1,"宜昌":1,"郑州":3,"温州":1,"保定":1,"长沙":1,"北京":3},"JEMA ROSE":{"天津":26,"乌鲁木齐":25,"廊坊":6,"成都":31,"苏州":24,"南充":3,"济南":7,"茂名":3,"河南":9,"吴江":5,"广州":46,"东莞":10,"长沙":13,"绍兴":11,"北京":40,"泰安":4,"江阴":3,"宁波":25,"上海":57,"杭州":33,"石家庄":5,"渭南":3,"佛山":15,"汕头":3,"盐城":5,"保定":5,"深圳":26,"云南":3,"温州":15,"昆明":3,"株洲":13,"三门峡":2,"江门":4,"大连":8,"德阳":3,"烟台":3,"银川":2,"莱芜":2,"惠州":3,"哈尔滨":14,"诸暨":1,"广西":4,"台州":28,"常德":4,"芜湖":4,"南京":17,"呼和浩特":3,"贵阳":2,"武汉":17,"枣庄":1,"聊城":1,"珠海":11,"镇江":4,"沧州":2,"太仓":1,"湖州":4,"淮安":2,"常州":6,"郑州":3,"鄂尔多斯":1,"梅州":2,"泸州":3,"青岛":7,"西安":9,"马鞍山":1,"柳州":2,"德州":3,"金华":7,"临沂":2,"鞍山":1,"玉溪":2,"嘉兴":4,"淄博":1,"扬州":4,"兰州":3,"潍坊":2,"自贡":1,"葫芦岛":1,"无锡":5,"中山":3,"湛江":2,"舟山":1,"曲靖":1,"福州":2,"丽水":3,"沈阳":6,"宜兴":2,"金坛":2,"大同":1,"邯郸":2,"南宁":2,"南通":2,"抚顺":1,"合肥":3,"常熟":10,"蓬莱":1,"连云港":2,"唐山":1,"临汾":3,"开封":2,"南昌":2,"衡水":3,"北海":1,"徐州":1,"泉州":1,"丹东":2},"KAREN MURRELL":{"芜湖":1,"武汉":2,"义乌":1,"昆明":1,"揭阳":1,"佛山":2,"吴江":1,"上海":2,"长春":1,"厦门":1,"河南":1,"嘉兴":1,"广西":3},"BREATH PEARLS":{"洛阳":2},"GO HEAITHY":{"南京":2,"上海":2,"廊坊":1,"泉州":1,"梅州":1,"吴江":1,"汕头":1,"天津":1,"南宁":1},"LANOLIN":{"河南":1,"上海":2,"成都":3,"南京":1,"台州":1,"长沙":1,"青岛":1,"武汉":3,"丹东":1,"沧州":1,"江门":1},"CEMOY":{"上海":1,"苏州":1},"VICKS":{"上海":1,"杭州":1,"广西":1,"天津":1},"PROSPAN":{"洛阳":1,"兰州":1,"昆明":2,"广西":6,"泉州":1,"石家庄":1},"GOAT":{"嘉兴":1,"昆明":1,"温州":3,"厦门":2,"济南":2,"库尔勒":1,"上海":2,"天津":1,"长沙":1,"北京":3,"常德":1,"佛山":1,"武汉":1},"BUY ON YOUR BEHALF":{"北京":1,"广西":2},"AROMATIC HERBS":{"成都":1,"云南":3,"南京":2,"温州":2,"呼和浩特":1,"广州":8,"丹东":1,"滨州":1,"葫芦岛":2,"抚顺":1,"武汉":3,"沈阳":1,"揭阳":1,"苏州":1,"宝鸡":1,"中山":2,"三门峡":1,"惠州":1,"上海":4,"青岛":1,"长沙":1,"汕头":1,"佛山":2,"深圳":3,"江门":1,"湖州":1,"天津":1,"金华":1,"昆明":1,"泸州":2,"郑州":1,"杭州":3,"潍坊":1,"沧州":1,"淮安":1,"绍兴":2,"哈尔滨":1,"常熟":1,"泉州":1,"烟台":2,"重庆":1},"SUDOCREM":{"杭州":1,"湖州":1,"上海":2},"DELIVERY TO CHINA":{"河南":1,"广西":2,"沈阳":1},"BOWRON GOLDSTAR":{"上海":1},"MEGA TEN":{"北京":2,"成都":1,"广西":1,"义乌":1},"HUBBARDS":{"成都":1,"长沙":1,"河南":1,"宜昌":1,"惠州":1,"无锡":1,"南京":1,"珠海":1,"北京":1},"LIFESTREAM":{"广西":1,"大连":4,"青岛":2},"XL.S MEDICAL":{"南昌":1,"洛阳":2,"河源":1},"JYP":{"宁波":1,"温州":1,"焦作":1,"广州":1,"淮安":1},"VOGEL'S":{"长沙":3,"苏州":2,"北京":3,"温州":1,"惠州":1,"宁波":1,"天津":8,"汕头":1},"CURASH":{"广西":1},"ARTEMIS":{"北京":3,"上海":1,"宁波":2,"柳州":2,"广州":2},"DIMPLES":{"武汉":1,"德州":2,"兰州":3,"呼和浩特":1,"湛江":6,"南京":8,"合肥":1,"绍兴":4,"银川":1,"宜兴":1,"大连":2,"芜湖":1,"邯郸":2,"临汾":1,"广州":2,"重庆":1,"温州":1,"成都":1,"库尔勒":2,"西安":2,"北京":1,"天津":1,"哈尔滨":2,"河南":1,"上海":1,"常熟":5,"佛山":1,"杭州":2,"深圳":2,"嘉兴":1,"青岛":1,"扬州":1,"福州":1},"MOOSE":{"乌鲁木齐":1,"杭州":1,"临汾":1},"GROVE":{"北京":1},"AVENE":{"揭阳":1,"武汉":1},"SUKIN":{"揭阳":1},"CENOVIS":{"揭阳":1},"TAUPO PURE":{"温州":1},"BELLAMYS":{"广州":1},"RICHGARDEN":{"沈阳":2},"GOOD HEALTH":{"沈阳":4},"HYDRODOL":{"湖州":1,"河源":1,"中山":1,"东莞":1,"南京":1,"义乌":1},"BOTEAROA":{"唐山":1,"宁波":1,"苏州":2,"深圳":4,"温州":1,"杭州":2,"广州":2,"吉林":1,"河南":1,"石家庄":1,"哈尔滨":1,"大连":1,"无锡":1,"淄博":1,"太仓":1,"寿光":1,"佛山":1,"绍兴":1,"珠海":1,"银川":1,"常熟":1,"北京":1},"BIOREVIVE":{"杭州":4,"嘉兴":1,"武汉":1,"金华":2,"张家口":1,"渭南":1,"北京":1,"太原":1,"上海":3,"绍兴":1,"天津":1,"福州":1,"温州":1},"VENUSTAS":{"成都":4},"ENCARE":{"杭州":6,"金华":5},"ARATAKI":{"河南":1,"深圳":1,"上海":1,"德阳":1},"GEORGE FOREMAN":{"长沙":1,"江阴":1,"金华":1,"大庆":1,"佛山":1},"CORNOR":{"苏州":1},"WHITTAKERS":{"广西":2},"HOPES RELIEF":{"杭州":1,"北京":1},"JACK & JILL":{"成都":1},"ONEONE":{"杭州":2,"成都":2,"济南":1,"三门峡":3,"沧州":1,"温州":3,"河南":2,"丽水":1,"北京":1,"苏州":1},"MALTESERS":{"杭州":6,"镇江":1,"济南":1,"广州":4,"金华":1,"温州":9,"泉州":1,"哈尔滨":3,"昆山":1,"上海":3,"吉林":1,"长沙":2,"北京":4,"常州":1,"苏州":2,"义乌":1,"宜兴":1,"西安":10},"PEEK":{"成都":4,"哈尔滨":1,"河南":1,"金华":1,"广州":2,"吉林":1,"佛山":2,"上海":3,"江阴":1,"宁波":1,"苏州":1,"温州":2,"嘉兴":1,"湖州":2,"杭州":2,"大同":1,"北京":2,"汕头":1,"宜兴":1,"绍兴":1,"深圳":1},"SIPAHH":{"北京":2},"BEAUTYECOLOGY":{"重庆":1},"GLOW LAB":{"嘉兴":6,"广州":2,"杭州":7,"上海":5,"珠海":2,"济南":1,"金华":3,"温州":7,"广西":2,"乌鲁木齐":3,"义乌":1,"中山":2,"深圳":2,"宜兴":1,"青岛":4,"衡水":1,"湖州":1,"韶关":1,"佛山":1},"A2":{"广西":1},"PHLOE":{"济南":1,"嘉兴":3},"BEAUTEOUS":{"石家庄":2},"NUTRA-LIFE":{"广州":1,"西安":1},"LELLURE":{"上海":1},"NP NATURAL & PURE":{"济宁":1},"PALMER'S":{"广州":1},"VOOST":{"汕头":2},"CHAMPION":{"韶关":1,"芜湖":1},"THERMOS":{"贵阳":1},"ANCHOR":{"桂林":2}}